ezeeml/__init__.py
ezeeml/data/__init__.py
ezeeml/data/fetcher.py
ezeeml/data/files.py
ezeeml/data/datasets/__init__.py
ezeeml/data/datasets/samplers.py
ezeeml/data/datasets/srpgan.py
ezeeml/eval/__init__.py
ezeeml/matplotlib/__init__.py
ezeeml/matplotlib/utils.py
ezeeml/pandas/__init__.py
ezeeml/pandas/cleaner.py
ezeeml/pandas/date.py
ezeeml/pandas/encoder.py
ezeeml/pandas/merger.py
ezeeml/pandas/splitter.py
ezeeml/pandas/tools.py
ezeeml/spark/__init__.py
ezeeml/tf/__init__.py
ezeeml/torch/__init__.py
ezeeml/torch/layers.py
ezeeml/torch/shortcuts.py
ezeeml/torch/test_callbacks.py
ezeeml/torch/train_callbacks.py
ezeeml/torch/transforms.py
ezeeml/torch/learner/__init__.py
ezeeml/torch/learner/cores.py
ezeeml/torch/losses/__init__.py
ezeeml/torch/losses/srpgan.py
ezeeml/torch/metrics/__init__.py
ezeeml/torch/models/__init__.py
ezeeml/torch/models/srpgan.py
ezeeml/torch/tools/__init__.py
ezeeml/torch/tools/image_tools.py
ezeeml/torch/tools/pytorch_modelsize.py
ezeeml/torch/tools/ssim.py
ezeeml/torch/tools/tensor_tools.py
ezeeml-0.1.0.dist-info/DESCRIPTION.rst
ezeeml-0.1.0.dist-info/METADATA
ezeeml-0.1.0.dist-info/RECORD
ezeeml-0.1.0.dist-info/WHEEL
ezeeml-0.1.0.dist-info/metadata.json
ezeeml-0.1.0.dist-info/top_level.txt
