Metadata-Version: 2.0
Name: ezeeml
Version: 0.1.0
Summary: A high level library for Pytorch
Home-page: https://github.com/EKami/EzeeML
Author: GODARD Tuatini
Author-email: tuatinigodard@gmail.com
License: MIT
Keywords: development
Platform: UNKNOWN
Classifier: Development Status :: 3 - Alpha
Classifier: Intended Audience :: Developers
Classifier: Topic :: Software Development :: Build Tools
Classifier: License :: OSI Approved :: MIT License
Classifier: Programming Language :: Python :: 3.4
Classifier: Programming Language :: Python :: 3.5
Classifier: Programming Language :: Python :: 3.6
Requires-Dist: isoweek
Requires-Dist: tqdm
Requires-Dist: bcolz
Requires-Dist: kaggle-data
Requires-Dist: opencv-python
Requires-Dist: scikit-image
Requires-Dist: setuptools
Requires-Dist: numpy
Requires-Dist: matplotlib
Requires-Dist: scipy
Requires-Dist: Pillow
Requires-Dist: dask
Requires-Dist: scikit-learn
Requires-Dist: tensorboardX
Requires-Dist: typing
Requires-Dist: PyYAML
Requires-Dist: Augmentor
Requires-Dist: ezeeml
